reactives/__init__.py
reactives/messenger.py
reactives/reactive.py
peach_reactives-0.0.6.dist-info/LICENSE
peach_reactives-0.0.6.dist-info/METADATA
peach_reactives-0.0.6.dist-info/WHEEL
peach_reactives-0.0.6.dist-info/top_level.txt
peach_reactives-0.0.6.dist-info/RECORD
