Metadata-Version: 2.1
Name: peach-reactives
Version: 0.0.6
Author-email: Peach <james@christhall.us>
Project-URL: Homepage, https://gitlab.com/peach_experiments/reactives
Requires-Python: >=3.10
License-File: LICENSE
